dropman/__init__.py
dropman/cli.py
dropman/commands/__init__.py
dropman/commands/base.py
dropman/commands/list.py
dropman/commands/powercycle.py
dropman/commands/poweroff.py
dropman/commands/poweron.py
dropman/commands/reboot.py
dropman/commands/shutdown.py
dropman-1.1.3.dist-info/LICENSE
dropman-1.1.3.dist-info/METADATA
dropman-1.1.3.dist-info/WHEEL
dropman-1.1.3.dist-info/entry_points.txt
dropman-1.1.3.dist-info/top_level.txt
dropman-1.1.3.dist-info/RECORD
