Metadata-Version: 2.1
Name: dropman
Version: 1.1.3
Summary: A CLI Tool to manage Digital Ocean Droplets.
Home-page: https://github.com/dcsg/dropman
Author: Daniel Gomes
Author-email: me@danielcsgomes.com
License: MIT
Keywords: digitalocean droplet droplets
Platform: UNKNOWN
Classifier: Development Status :: 5 - Production/Stable
Classifier: Environment :: Console
Classifier: Intended Audience :: Developers
Classifier: Intended Audience :: System Administrators
Classifier: Topic :: Utilities
Classifier: License :: OSI Approved :: MIT License
Classifier: Natural Language :: English
Classifier: Operating System :: OS Independent
Classifier: Programming Language :: Python :: 3
Classifier: Programming Language :: Python :: 3.0
Classifier: Programming Language :: Python :: 3.1
Classifier: Programming Language :: Python :: 3.2
Classifier: Programming Language :: Python :: 3.3
Classifier: Programming Language :: Python :: 3.4
Classifier: Programming Language :: Python :: 3.5
Classifier: Programming Language :: Python :: 3.6
Classifier: Programming Language :: Python :: 3 :: Only
Requires-Dist: docopt (==0.6.2)
Requires-Dist: pyyaml (>=4.2b1)
Requires-Dist: tabulate (==0.7.5)
Requires-Dist: python-digitalocean (==1.9.0)
Provides-Extra: test
Requires-Dist: coverage ; extra == 'test'
Requires-Dist: pytest ; extra == 'test'
Requires-Dist: pytest-cov ; extra == 'test'
